vit_prisma/__init__.py
vit_prisma/configs/CircleConfig.py
vit_prisma/configs/DSpritesConfig.py
vit_prisma/configs/HookedViTConfig.py
vit_prisma/configs/InductionConfig.py
vit_prisma/configs/MNISTConfig.py
vit_prisma/configs/__init__.py
vit_prisma/configs/timmConfigs/__init__.py
vit_prisma/configs/timmConfigs/vit_base_patch32_224_Config.py
vit_prisma/dataloaders/__init__.py
vit_prisma/dataloaders/cifar10.py
vit_prisma/dataloaders/circle.py
vit_prisma/dataloaders/dsprites.py
vit_prisma/dataloaders/induction.py
vit_prisma/dataloaders/polygenic_induction.py
vit_prisma/models/__init__.py
vit_prisma/models/activation_fns.py
vit_prisma/models/base_vit.py
vit_prisma/models/dictionaries.py
vit_prisma/models/prisma_net.py
vit_prisma/models/layers/__init__.py
vit_prisma/models/layers/attention.py
vit_prisma/models/layers/head.py
vit_prisma/models/layers/layer_norm.py
vit_prisma/models/layers/mlp.py
vit_prisma/models/layers/patch_embedding.py
vit_prisma/models/layers/position_embedding.py
vit_prisma/models/layers/transformer_block.py
vit_prisma/prisma_tools/__init__.py
vit_prisma/prisma_tools/activation_cache.py
vit_prisma/prisma_tools/factored_matrix.py
vit_prisma/prisma_tools/hook_point.py
vit_prisma/prisma_tools/hooked_root_module.py
vit_prisma/prisma_tools/lens_handle.py
vit_prisma/prisma_tools/loading_from_pretrained.py
vit_prisma/prisma_tools/logit_lens.py
vit_prisma/training/__init__.py
vit_prisma/training/early_stopping.py
vit_prisma/training/schedulers.py
vit_prisma/training/trainer.py
vit_prisma/training/training_dictionary.py
vit_prisma/training/training_utils.py
vit_prisma/utils/__init__.py
vit_prisma/utils/devices.py
vit_prisma/utils/get_activations.py
vit_prisma/utils/prisma_utils.py
vit_prisma/utils/saving_utils.py
vit_prisma/utils/wandb_utils.py
vit_prisma/utils/data_utils/__init__.py
vit_prisma/utils/data_utils/imagenet_dict.py
vit_prisma/utils/data_utils/imagenet_emoji.py
vit_prisma/utils/data_utils/imagenet_utils.py
vit_prisma/utils/imagenet/__init__.py
vit_prisma-0.1.4.dist-info/METADATA
vit_prisma-0.1.4.dist-info/WHEEL
vit_prisma-0.1.4.dist-info/top_level.txt
vit_prisma-0.1.4.dist-info/RECORD
