Metadata-Version: 2.1
Name: vit-prisma
Version: 0.1.4
Summary: A Vision Transformer library for mechanistic interpretability.
Home-page: https://github.com/soniajoseph/vit-prisma
Author: Sonia Joseph
Author-email: soniamollyjoseph@gmail.com
Keywords: vision-transformer,clip,multimodal,machine-learning,mechanistic interpretability
Classifier: Programming Language :: Python :: 3
Classifier: License :: OSI Approved :: MIT License
Classifier: Operating System :: OS Independent
Classifier: Intended Audience :: Science/Research
Classifier: Topic :: Scientific/Engineering :: Artificial Intelligence
Requires-Python: >=3.6
Requires-Dist: pytest >=6.0
Requires-Dist: torch
Requires-Dist: numpy
Requires-Dist: jaxtyping
Requires-Dist: einops
Requires-Dist: fancy-einsum
Requires-Dist: plotly ==5.19.0
Requires-Dist: timm
Requires-Dist: transformers
Requires-Dist: scikit-learn
Requires-Dist: datasets
